scuq/LICENSE
scuq/__init__.py
scuq/arithmetic.py
scuq/cucomponents.py
scuq/operators.py
scuq/qexceptions.py
scuq/quantities.py
scuq/si.py
scuq/testcases.py
scuq/ucomponents.py
scuq/units.py
scuq-0.9.1.dist-info/licenses/LICENSE
scuq-0.9.1.dist-info/WHEEL
scuq-0.9.1.dist-info/METADATA
scuq-0.9.1.dist-info/RECORD
